infrabot/__init__.py
infrabot/ai/__init__.py
infrabot/ai/chat.py
infrabot/ai/completion.py
infrabot/ai/config.py
infrabot/ai/summary.py
infrabot/ai/terraform_generator.py
infrabot/api.py
infrabot/cli.py
infrabot/infra_utils/__init__.py
infrabot/infra_utils/component_manager.py
infrabot/infra_utils/terraform.py
infrabot/utils/__init__.py
infrabot/utils/file_cache.py
infrabot/utils/logging_config.py
infrabot/utils/os.py
infrabot/utils/parsing.py
infrabot-0.1.1.dist-info/AUTHORS.rst
infrabot-0.1.1.dist-info/LICENSE
infrabot-0.1.1.dist-info/METADATA
infrabot-0.1.1.dist-info/WHEEL
infrabot-0.1.1.dist-info/entry_points.txt
infrabot-0.1.1.dist-info/RECORD
