Metadata-Version: 2.3
Name: infrabot
Version: 0.1.1
Summary: Create resource on the cloud with natural language
License: MIT
Author: Alaeddine Abdessalem
Author-email: alaeddine.abdessalem@gmail.com
Maintainer: Alaeddine Abdessalem
Maintainer-email: alaeddine.abdessalem@gmail.com
Requires-Python: >3.10,<4.0
Classifier: License :: OSI Approved :: MIT License
Classifier: Programming Language :: Python :: 3
Classifier: Programming Language :: Python :: 3.11
Classifier: Programming Language :: Python :: 3.12
Classifier: Programming Language :: Python :: 3.13
Provides-Extra: dev
Requires-Dist: click (>=8.1.7,<9.0.0)
Requires-Dist: coverage ; extra == "dev"
Requires-Dist: litellm (>=1.57.1,<2.0.0)
Requires-Dist: mypy ; extra == "dev"
Requires-Dist: openai (>=1.53.0,<2.0.0)
Requires-Dist: pytest ; extra == "dev"
Requires-Dist: ruff ; extra == "dev"
Requires-Dist: typer (>=0.12.5,<0.13.0)
Project-URL: Homepage, https://github.com/alaeddine-13/infrabot
Project-URL: bugs, https://github.com/alaeddine-13/infrabot/issues
Project-URL: changelog, https://github.com/alaeddine-13/infrabot/blob/master/changelog.md
